cronpar/__init__.py
cronpar/api.py
cronpar/cli.py
cronpar/handler.py
cronpar-1.0.0.dist-info/entry_points.txt
cronpar-1.0.0.dist-info/WHEEL
cronpar-1.0.0.dist-info/METADATA
cronpar-1.0.0.dist-info/RECORD
