Metadata-Version: 2.1
Name: cronpar
Version: 1.0.0
Summary: A Cron Expression Parser
Author: Liusha He
Requires-Python: >=3.8.1,<3.12
Classifier: Programming Language :: Python :: 3
Classifier: Programming Language :: Python :: 3.9
Classifier: Programming Language :: Python :: 3.10
Requires-Dist: click (>=8.1.7,<9.0.0)
